asgi_websub/__init__.py
asgi_websub/hub.py
asgi_websub/middleware.py
asgi_websub/publisher.py
asgi_websub/subscriber.py
asgi_websub-0.0.1.dist-info/LICENSE
asgi_websub-0.0.1.dist-info/WHEEL
asgi_websub-0.0.1.dist-info/METADATA
asgi_websub-0.0.1.dist-info/RECORD
